M10to1.v
`timescale 1ns/1ps
module M10to1(
  input I0, I1, I2, I3, I4, I5, I6, I7, I8, I9, S0, S1, S2, S3, 
  output out
	);
	wire T1, T2, T3, T4, T5, T6, T7, T8, T9, T10, T11, T12, T13, T14;
	not(T1, S0);
	not(T2, S1);
	not(T3, S2);
	not(T4, S3);
	and(T5, I0, T1, T2, T3, T4), (T6, I1, S0, T2, T3, T4);
	and(T7, I2, T1, S1, T3, T4), (T8, I3, S0, S1, T3, T4);
	and(T9, I4, T1, T2, S2, T4), (T10, I5, S0, T2, S2, T4);
	and(T11, I6, T1, S1, S2, T4), (T12, I7, S0, S1, S2, T4);
	and(T13, I8, T1, T2, T3, S3), (T14, I9, S0, T2, T3, S3);
	or(out, T5, T6, T7, T8, T9, T10, T11, T12, T13, T14);

endmodule

M10to1.vcd
$version Generated by VerilatedVcd $end
$date Sun Feb 20 22:40:52 2022
 $end
$timescale   1ns $end

 $scope module TOP $end
  $var wire  1 # I0 $end
  $var wire  1 + I1 $end
  $var wire  1 3 I2 $end
  $var wire  1 ; I3 $end
  $var wire  1 C I4 $end
  $var wire  1 K I5 $end
  $var wire  1 S I6 $end
  $var wire  1 [ I7 $end
  $var wire  1 c I8 $end
  $var wire  1 k I9 $end
  $var wire  1 s S0 $end
  $var wire  1 { S1 $end
  $var wire  1 %! S2 $end
  $var wire  1 -! S3 $end
  $var wire  1 5! out $end
  $scope module M10to1 $end
   $var wire  1 # I0 $end
   $var wire  1 + I1 $end
   $var wire  1 3 I2 $end
   $var wire  1 ; I3 $end
   $var wire  1 C I4 $end
   $var wire  1 K I5 $end
   $var wire  1 S I6 $end
   $var wire  1 [ I7 $end
   $var wire  1 c I8 $end
   $var wire  1 k I9 $end
   $var wire  1 s S0 $end
   $var wire  1 { S1 $end
   $var wire  1 %! S2 $end
   $var wire  1 -! S3 $end
   $var wire  1 =! T1 $end
   $var wire  1 '" T10 $end
   $var wire  1 /" T11 $end
   $var wire  1 7" T12 $end
   $var wire  1 ?" T13 $end
   $var wire  1 G" T14 $end
   $var wire  1 E! T2 $end
   $var wire  1 M! T3 $end
   $var wire  1 U! T4 $end
   $var wire  1 ]! T5 $end
   $var wire  1 e! T6 $end
   $var wire  1 m! T7 $end
   $var wire  1 u! T8 $end
   $var wire  1 }! T9 $end
   $var wire  1 5! out $end
  $upscope $end
 $upscope $end
$enddefinitions $end


#0
0#
1+
13
1;
0C
1K
1S
0[
0c
1k
1s
1{
0%!
1-!
05!
0=!
0E!
1M!
0U!
0]!
0e!
0m!
0u!
0}!
0'"
0/"
07"
0?"
0G"
#1
03
0S
0{
0-!
1E!
1U!
1e!
#2
0+
0;
1C
1[
1-!
15!
0U!
0e!
1G"
#3
0K
1S
0[
0k
0s
1%!
1=!
0M!
0G"
#4
1+
13
1;
1c
1k
0%!
05!
1M!
1?"
#5
03
0;
1K
0S
1[
0k
1s
1{
15!
0=!
0E!
0?"
#6
0C
1S
1k
05!
#7
1#
13
1;
0S
0c
0k
0s
0{
1=!
1E!
#8
0+
03
1C
0K
1k
1{
0-!
0E!
1U!
#9
0#
1+
13
0C
1S
0[
1s
0{
1%!
0=!
1E!
0M!
#10
0+
0;
#11
1+
03
1K
0S
0s
0%!
1=!
1M!
#12
1;
1C
1S
1c
0k
1-!
0U!
1?"
#13
13
0;
0C
1[
1k
1s
1{
0-!
15!
0=!
0E!
1U!
0?"
#14
1#
0+
03
1;
1C
0K
0S
1-!
05!
0U!
#15
0s
0{
0-!
1=!
1E!
1U!
1]!
#16
0;
0C
0c
0k
1{
1-!
15!
0E!
0U!
0]!
#17
0#
1;
1K
1S
1c
1k
0{
05!
1E!
1?"
#18
1#
13
0;
0[
1s
1{
1%!
0-!
15!
0=!
0E!
0M!
1U!
0?"
#19
0#
1+
1;
1C
0K
0S
1[
0s
0{
0%!
1-!
05!
1=!
1E!
1M!
0U!
1?"
#20
0+
03
0C
1K
0[
0c
1{
0-!
15!
0E!
1U!
0?"
#21
1+
0;
1C
1S
1c
0k
0{
1%!
05!
1E!
0M!
1}!
#22
0+
13
1;
0C
0S
1[
0c
1s
15!
0=!
0}!
1'"
#23
1#
1+
03
1C
0K
0[
1c
1k
0s
1{
1=!
0E!
0'"
#24
13
0;
1S
1[
0c
0{
0%!
05!
1E!
1M!
1]!
#25
03
0S
0[
0k
1{
1%!
15!
0E!
0M!
0]!
#26
0#
13
0C
1[
1k
0{
0%!
1-!
05!
1E!
1M!
0U!
#27
1#
0+
1K
1c
0k
1s
1{
0=!
0E!
#28
0#
1;
1C
0K
1S
0c
1k
0s
0-!
1=!
1U!
1m!
#29
1#
0;
0S
1c
0{
1%!
1-!
15!
1E!
0M!
0U!
0m!
#30
03
0C
1K
1S
0c
0k
0-!
05!
1U!
#31
1+
1;
1C
0K
0[
1s
1-!
0=!
0U!
#32
0#
0+
0;
0C
0S
1k
#33
13
1C
1S
0k
0%!
0-!
1M!
1U!
#34
1+
03
1;
0C
1c
1k
1{
0E!
1u!
#35
1#
1C
1K
0k
0s
1%!
1-!
15!
1=!
0M!
0U!
0u!
#36
0#
0;
0K
1[
0c
1s
0-!
05!
0=!
1U!
17"
#37
13
1;
0C
1K
0{
15!
1E!
1'"
07"
#38
1#
0+
1C
0S
0[
1c
1k
0%!
1-!
1M!
0U!
0'"
1G"
#39
1+
0;
0K
1S
1[
0k
1%!
0-!
0M!
1U!
0G"
#40
0#
0+
03
1;
0C
1k
0s
1{
0%!
1-!
05!
1=!
0E!
1M!
0U!
#41
1#
0;
0S
0c
0k
0{
1E!
#42
0#
1+
1C
1S
1s
1%!
0=!
0M!
#43
1#
0+
0C
1K
0S
0[
1c
1k
1{
0-!
0E!
1U!
#44
1+
13
1;
1C
1S
0c
0s
0{
1-!
1=!
1E!
0U!
#45
0#
03
0K
1[
1c
0k
#46
0+
13
1K
0[
0c
1s
0=!
#47
1#
1+
03
0C
0K
1[
0s
0%!
0-!
1=!
1M!
1U!
1]!
#48
0#
0;
1C
1K
0S
1k
1s
1{
1%!
15!
0=!
0E!
0M!
0]!
17"
#49
1#
13
0C
0[
1c
0{
1-!
1E!
0U!
07"
#50
0#
0+
03
1C
0K
1S
1[
0s
0%!
05!
1=!
1M!
1?"
#51
1#
1+
0C
1K
0[
15!
#52
0#
13
1C
1[
0k
1%!
0-!
0M!
1U!
1}!
0?"
#53
1;
0C
0S
1k
1s
0%!
0=!
1M!
1e!
0}!
#54
0+
1C
0K
1S
0k
0s
1=!
0e!
#55
1#
1+
03
0C
1K
1k
1-!
05!
0U!
1?"
#56
0#
0+
13
0;
1{
1%!
0-!
15!
0E!
0M!
1U!
1/"
0?"
#57
1#
03
1C
0K
0S
0[
0c
1s
0%!
1-!
0=!
1M!
0U!
0/"
#58
1;
0C
1S
1c
0{
0-!
05!
1E!
1U!
#59
1+
1C
1K
1[
1{
0E!
1u!
#60
0#
0+
13
0C
0S
0[
0k
0s
0{
1%!
15!
1=!
1E!
0M!
0u!
#61
1#
1+
03
0;
0K
1S
1k
1s
1{
0%!
05!
0=!
0E!
1M!
#62
0#
1;
1C
1K
0S
0c
0s
0{
1%!
1-!
1=!
1E!
0M!
0U!
#63
0+
13
1[
1c
1s
1{
0%!
0-!
0=!
0E!
1M!
1U!
1u!
#64
1+
03
0;
0C
0K
1S
0k
0{
1%!
15!
1E!
0M!
0u!
#65
0+
13
0S
0s
05!
1=!
#66
1#
03
1;
1C
1K
1k
1{
0E!
#67
0C
1S
0[
1s
0{
0=!
1E!
1'"
#68
0#
1+
0;
1C
0K
1{
1-!
15!
0E!
0U!
0'"
#69
0+
13
1;
1K
0S
1[
0c
0s
05!
1=!
#70
1#
0;
0[
#71
0#
0C
0K
1S
1[
1s
0{
0=!
1E!
#72
03
1;
0[
1c
0s
1{
1=!
0E!
#73
1#
1K
0S
0c
0{
1E!
#74
0#
0;
0K
#75
1#
0k
0-!
1U!
#76
0#
13
1K
1S
1k
1s
0%!
1-!
0=!
1M!
0U!
1G"
#77
1+
03
1C
0K
0S
1[
1c
0k
1{
0-!
15!
0E!
1U!
0G"
#78
1#
0+
1;
0C
1S
1%!
05!
0M!
17"
#79
0#
0;
1C
0S
1k
0s
0{
15!
1=!
1E!
1}!
07"
#80
1#
0C
1S
0[
0c
0k
1s
1-!
0=!
0U!
0}!
#81
13
1;
1K
0S
1{
05!
0E!
#82
1+
0;
1C
1[
1k
0{
1E!
#83
0#
0+
03
1S
1c
1{
0%!
0-!
0E!
1M!
1U!
#84
1+
1;
0C
0s
1=!
#85
1#
13
0;
0S
0c
1%!
0M!
#86
0#
03
0K
1S
0k
1-!
0U!
#87
13
1;
1C
1c
1k
0-!
1U!
1/"
#88
1#
0+
03
1K
0S
0%!
1-!
15!
1M!
0U!
0/"
#89
0#
1+
0;
0[
1s
0{
1%!
05!
0=!
1E!
0M!
#90
1#
0+
13
0C
0K
1[
0k
0s
1=!
#91
0#
1+
03
1C
1S
0[
1k
0%!
1M!
1?"
#92
1;
1K
0S
1[
0k
15!
#93
1#
0K
1S
0[
0c
1{
1%!
0-!
0E!
0M!
1U!
1/"
0?"
#94
0+
13
1K
0S
1[
0{
0%!
1-!
1E!
1M!
0U!
0/"
#95
0#
03
0C
0K
1s
05!
0=!
#96
1#
13
0;
1S
1c
1k
0s
1{
1=!
0E!
#97
03
1C
0c
0k
0{
1E!
#98
0#
1;
0C
1K
0[
1c
1%!
0-!
0M!
1U!
#99
1#
1+
13
1[
1{
0%!
0E!
1M!
1m!
#100
0+
1C
0S
0c
1k
1%!
15!
0M!
0m!
#101
1+
03
0;
0C
0K
1S
0[
1c
0k
1s
1-!
05!
0=!
0U!
#102
0#
13
1[
0s
0-!
1=!
1U!
1/"
#103
03
1;
1K
0S
0[
1k
1s
0{
0%!
15!
0=!
1E!
1M!
1e!
0/"
#104
1#
0;
0c
1{
1%!
0E!
0M!
0e!
#105
1;
1S
0s
0%!
1-!
05!
1=!
1M!
0U!
#106
0+
1C
0K
1c
0-!
1U!
#107
0;
1[
0k
1s
1%!
1-!
0=!
0M!
0U!
#108
0#
13
0C
1K
0[
0s
0{
0-!
1=!
1E!
1U!
#109
1+
03
1;
1C
0K
1s
0=!
#110
0+
0;
0C
1K
0S
1[
0c
1k
1{
1-!
0E!
0U!
#111
1#
13
1;
0K
0s
0%!
1=!
1M!
#112
0#
1+
03
0;
1C
0[
1c
1s
0-!
0=!
1U!
#113
0+
13
1;
0C
1S
0c
0s
1%!
1=!
0M!
1/"
#114
1+
0;
1K
0S
1[
1c
1s
0{
0%!
15!
0=!
1E!
1M!
1e!
0/"
#115
1#
0+
03
1;
1S
0c
0k
1%!
1-!
0M!
0U!
0e!
#116
13
0;
1C
0S
1k
0%!
0-!
05!
1M!
1U!
#117
0#
0C
1S
1c
0k
0s
1{
1-!
1=!
0E!
0U!
#118
1#
1;
0K
0[
1k
1s
0{
0-!
0=!
1E!
1U!
#119
0#
0;
0S
1[
0k
0s
1=!
#120
1#
1+
1;
1C
1k
1s
1-!
0=!
0U!
1G"
#121
0#
0;
1S
0[
0c
1%!
15!
0M!
0G"
#122
0+
1c
0%!
05!
1M!
1G"
#123
03
1;
1K
1[
0c
0k
0-!
15!
1U!
0G"
#124
1+
13
0K
0[
0s
1{
1%!
05!
1=!
0E!
0M!
1/"
#125
1#
0;
1K
1[
0{
1-!
15!
1E!
0U!
0/"
#126
1;
0C
0K
0S
0[
1k
05!
#127
0#
0+
1C
1S
1[
1c
0k
1{
0-!
0E!
1U!
1/"
#128
0S
0c
1k
1s
0{
0%!
15!
0=!
1E!
1M!
0/"
#129
0;
0C
0[
1{
1-!
05!
0E!
0U!
#130
1+
1C
1S
0k
0{
1%!
1E!
0M!
#131
1k
0s
0%!
1=!
1M!
#132
1#
0+
03
1;
1K
0S
1c
1{
1%!
0-!
0E!
0M!
1U!
#133
13
0C
0K
1S
1[
0c
0k
1s
0{
1-!
0=!
1E!
0U!
#134
0#
03
0S
0[
1c
0s
0%!
1=!
1M!
1?"
#135
1#
1+
13
0;
1S
0c
1k
1s
1%!
15!
0=!
0M!
0?"
#136
0#
03
1C
1K
1[
1c
1{
0%!
0-!
05!
0E!
1M!
1U!
#137
1#
0+
13
1;
0K
0c
0{
1-!
1E!
0U!
1G"
#138
0#
1+
03
0;
0C
0S
1c
1{
0-!
15!
0E!
1U!
0G"
#139
0+
1;
1K
0[
0k
1%!
1-!
05!
0M!
0U!
#140
1#
1+
0K
1S
1[
0c
1k
0s
0{
0%!
1=!
1E!
1M!
#141
1C
0S
0[
1{
1%!
0E!
0M!
#142
0+
0;
1[
#143
1+
0C
1S
0[
1c
0%!
0-!
1M!
1U!
#144
0#
13
1;
1C
0S
0c
0k
1%!
0M!
#145
0+
0C
1S
1/"
#146
03
1C
0S
1[
1s
0{
0%!
1-!
15!
0=!
1E!
1M!
0U!
0/"
#147
1#
0C
1K
0[
1c
1k
1%!
05!
0M!
#148
1+
0;
1C
0K
1S
0c
0%!
1M!
1G"
#149
0+
0C
0S
1[
0k
1{
0-!
15!
0E!
1U!
0G"
#150
1+
1;
1S
0s
1%!
1-!
05!
1=!
0M!
0U!
#151
0;
1K
0[
1c
1k
1s
0=!
#152
13
1C
1[
0k
0{
0%!
1E!
1M!
#153
0+
03
0c
0s
1{
1%!
1=!
0E!
0M!
#154
0C
0K
0S
1c
0%!
1M!
#155
1+
1C
1K
0[
0c
1k
0{
1%!
0-!
1E!
0M!
1U!
1}!
#156
0+
13
0K
1[
1{
15!
0E!
0}!
#157
0#
1+
03
1;
0C
1S
1c
0k
05!
1/"
#158
1#
1C
1K
0[
1s
1-!
15!
0=!
0U!
0/"
#159
0+
0K
0c
0{
0%!
05!
1E!
1M!
#160
13
1K
0S
1c
1k
1%!
0-!
0M!
1U!
1'"
#161
0#
03
0C
0K
0c
0s
0%!
1-!
15!
1=!
1M!
0U!
0'"
#162
13
0;
1S
1[
1{
05!
0E!
#163
1#
1;
1K
0S
1c
1s
0=!
#164
0#
03
0;
1C
0c
0{
1E!
1G"
#165
1#
1+
1c
0k
0s
1%!
15!
1=!
0M!
0G"
#166
0#
0+
0C
0c
1k
1s
0%!
0-!
05!
0=!
1M!
1U!
#167
1+
13
1;
0k
0s
1{
1-!
1=!
0E!
0U!
#168
0+
03
0;
0[
0{
1%!
1E!
0M!
#169
1#
13
1;
1C
0K
1S
1[
1c
1k
1{
0-!
0E!
1U!
1/"
#170
1+
15!
#171
0;
0S
0[
0c
1s
0%!
1-!
0=!
1M!
0U!
0/"
#172
0#
1;
0C
1K
1c
0{
05!
1E!
1G"
#173
1#
0+
0;
1C
0K
1S
0c
0s
15!
1=!
0G"
#174
03
1K
1[
0k
1s
1{
1%!
05!
0=!
0E!
0M!
#175
0C
0K
#176
1+
1;
1C
0[
1c
0{
0%!
1E!
1M!
#177
0+
0C
0c
1{
0-!
0E!
1U!
1u!
#178
0#
1+
13
1K
0S
1[
1c
1k
0{
1-!
15!
1E!
0U!
0u!
1G"
#179
0+
03
0;
0K
1S
0[
0c
0k
0s
1{
1%!
1=!
0E!
0M!
0G"
#180
1+
13
1C
1[
1c
1s
0{
0-!
05!
0=!
1E!
1U!
#181
1#
1;
0C
1K
0[
1-!
0U!
#182
0+
1C
0K
0s
0%!
1=!
1M!
1?"
#183
0;
1K
1[
0c
1k
1%!
15!
0M!
0?"
#184
0#
03
1;
0C
0S
0[
1{
0-!
05!
0E!
1U!
#185
1#
13
0;
1[
0k
1s
0{
1-!
0=!
1E!
0U!
#186
0#
03
1C
0K
1S
1k
0%!
0-!
1M!
1U!
#187
1#
0C
0[
1c
1{
1%!
0E!
0M!
#188
13
1C
1K
0S
0c
0k
0{
1-!
1E!
0U!
#189
0#
1;
0C
1S
1c
0s
0%!
1=!
1M!
1?"
#190
1#
1+
03
1[
1k
1s
1{
1%!
0-!
15!
0=!
0E!
0M!
1U!
17"
0?"
#191
13
1C
0K
0S
0c
0%!
1-!
1M!
0U!
07"
#192
0#
0+
03
0s
1%!
05!
1=!
0M!
#193
1K
0[
0k
1s
0{
0-!
0=!
1E!
1U!
1'"
#194
1#
1+
13
0K
1S
1[
1k
0s
1-!
15!
1=!
0U!
0'"
#195
0+
03
0C
0S
0[
0k
0%!
0-!
05!
1M!
1U!
1]!
#196
0#
1C
1S
1[
1%!
15!
0M!
0]!
1}!
#197
1#
13
0;
0C
0S
1s
1-!
0=!
0U!
0}!
#198
0#
1+
1C
1k
0s
0-!
05!
1=!
1U!
1}!
#199
0+
03
1;
0k
0%!
1-!
15!
1M!
0U!
0}!
#200
1#
1+
13
0[
1s
1%!
05!
0=!
0M!
#201
0#
0+
0C
1[
0%!
1M!
#202
1+
1S
1k
0s
1{
1%!
1=!
0E!
0M!
#203
1#
0+
0;
0[
0{
0%!
1E!
1M!
#204
0#
03
1;
1C
1K
0S
1c
1s
0=!
1G"
#205
1#
1+
13
0;
0K
1[
0c
0s
1{
1%!
0-!
15!
1=!
0E!
0M!
1U!
0G"
#206
1K
1S
1c
1s
0{
05!
0=!
1E!
1'"
#207
0#
03
1;
0S
0[
0k
0s
1{
0%!
15!
1=!
0E!
1M!
0'"
#208
0;
0C
1[
0c
1k
1-!
05!
0U!
#209
1C
0K
0[
1c
0k
0{
0-!
1E!
1U!
#210
1#
0+
1[
1s
1%!
1-!
0=!
0M!
0U!
#211
1+
13
1;
1K
0[
0s
0%!
0-!
1=!
1M!
1U!
1]!
#212
0#
0+
1S
0c
1k
1{
1%!
1-!
15!
0E!
0M!
0U!
0]!
#213
1#
03
0C
0S
1[
0k
1s
0%!
05!
0=!
1M!
#214
13
1C
0K
1S
0[
0s
0{
0-!
1=!
1E!
1U!
1]!
#215
1+
0C
0S
1c
1s
1%!
15!
0=!
0M!
0]!
#216
1[
1k
1{
0%!
1-!
05!
0E!
1M!
0U!
#217
0+
03
0;
1C
1K
1S
0-!
1U!
#218
1+
0C
0[
0c
0k
1%!
0M!
#219
0#
1;
1C
0K
1[
1c
1k
0s
0%!
1=!
1M!
#220
0+
1K
0[
0c
0{
1%!
1E!
0M!
1}!
#221
1#
0C
0K
0S
1[
0k
1-!
15!
0U!
0}!
#222
1+
13
1K
1k
1s
1{
0%!
0-!
05!
0=!
0E!
1M!
1U!
1u!
#223
03
0K
0[
1c
1%!
15!
0M!
0u!
#224
0+
13
0;
1C
1S
1[
0{
05!
1E!
#225
1+
03
0k
#226
0+
1;
0C
1K
1k
1{
0%!
0E!
1M!
1u!
#227
1+
0;
1C
0S
0[
0k
0{
15!
1E!
1e!
0u!
#228
0#
1S
1[
0c
0s
1%!
1-!
1=!
0M!
0U!
0e!
#229
1#
0+
13
0K
0S
0[
1c
0%!
05!
1M!
1?"
#230
1;
1S
1s
1{
1%!
0-!
15!
0=!
0E!
0M!
1U!
0?"
#231
0;
0C
1K
0S
0s
0{
1-!
05!
1=!
1E!
0U!
#232
0#
1+
03
1;
0K
1S
1[
0c
1{
0E!
#233
0+
13
0;
1K
0S
1k
1s
0=!
#234
1#
03
1;
1S
0[
1c
0k
0%!
1M!
#235
0#
1+
13
0;
1C
0K
0S
1k
0-!
1U!
#236
1;
0C
1S
0k
0s
0{
1-!
1=!
1E!
0U!
1?"
#237
1#
0+
1[
0c
1s
1%!
0-!
15!
0=!
0M!
1U!
0?"
#238
1+
03
0;
0[
0s
1{
0%!
05!
1=!
0E!
1M!
#239
0+
1C
1K
1[
1c
#240
1+
1;
0C
1s
1%!
0=!
0M!
17"
#241
0#
0K
0s
0{
0%!
15!
1=!
1E!
1M!
07"
#242
1K
0S
0c
1k
1{
1-!
05!
0E!
0U!
#243
13
0;
0K
1S
0[
0k
1s
0{
0=!
1E!
#244
0+
03
1C
0S
1c
1{
0E!
#245
1[
0c
1k
0s
0{
1%!
1=!
1E!
0M!
#246
1+
13
1;
0C
1K
1S
1c
1s
1{
0%!
0-!
0=!
0E!
1M!
1U!
1u!
#247
0+
0K
0c
0k
0s
0{
1%!
15!
1=!
1E!
0M!
0u!
#248
1+
03
1K
0S
0[
1k
1{
1-!
05!
0E!
0U!
#249
1C
1[
1c
0-!
1U!
#250
1#
13
0;
0C
1S
0[
0c
1s
0{
0%!
1-!
0=!
1E!
1M!
0U!
1G"
#251
03
0K
1[
0s
1{
0-!
15!
1=!
0E!
1U!
0G"
#252
0+
13
1C
0S
1c
1s
05!
0=!
#253
1+
0C
0c
0s
0{
1-!
1=!
1E!
0U!
#254
0#
1;
1C
1S
0[
0k
1s
1{
1%!
0-!
0=!
0E!
0M!
1U!
#255
0+
0S
1[
0s
0%!
1-!
1=!
1M!
0U!
#256
1#
03
1K
0[
0{
1E!
#257
0#
1+
0;
1c
0-!
1U!
#258
1#
0+
13
1s
1{
1-!
0=!
0E!
0U!
#259
1;
0C
1[
0c
0s
0-!
1=!
1U!
1m!
#260
03
0;
1C
0K
1S
0[
1c
1k
0{
1%!
1-!
15!
1E!
0M!
0U!
0m!
#261
13
1;
0C
0S
0k
1{
0%!
0-!
05!
0E!
1M!
1U!
1m!
#262
0#
03
0;
1C
0c
1k
0{
15!
1E!
0m!
#263
0C
1K
1S
1c
1s
1-!
05!
0=!
0U!
1G"
#264
1#
13
1;
1C
0k
0s
1%!
0-!
15!
1=!
0M!
1U!
1}!
0G"
#265
0#
03
0;
0C
0K
0S
1k
1-!
0U!
0}!
#266
1+
1;
1C
1K
1S
0c
0k
0%!
0-!
05!
1M!
1U!
#267
0+
0;
0C
0S
1c
1k
1{
0E!
#268
1#
1+
0K
1S
0c
0k
0{
1%!
1-!
1E!
0M!
0U!
#269
0#
13
1C
0S
1[
1c
1k
1s
0%!
0=!
1M!
1G"
#270
1#
0+
03
1;
0C
1S
0[
0c
0k
0s
1%!
15!
1=!
0M!
0G"
#271
1C
1K
0S
1[
1c
0-!
05!
1U!
1}!
#272
1+
13
0;
0C
1S
0[
1-!
15!
0U!
0}!
#273
0#
0+
03
1;
0K
1[
1k
1{
05!
0E!
#274
1#
1+
13
0;
0[
0c
0k
#275
0+
03
1s
0-!
0=!
1U!
#276
0#
1+
13
0S
1k
0{
0%!
1-!
1E!
1M!
0U!
1G"
#277
03
1;
1C
1S
1[
1%!
0-!
15!
0M!
1U!
0G"
#278
0;
0C
1K
0S
0[
1c
0s
0%!
1-!
05!
1=!
1M!
0U!
1?"
#279
0+
13
1C
0c
1s
0-!
15!
0=!
1U!
0?"
#280
1#
1;
1S
1[
1c
0k
1%!
1-!
05!
0M!
0U!
#281
0#
1+
0C
0K
1k
0s
1{
1=!
0E!
#282
03
1C
1K
0S
0[
0c
1s
0-!
0=!
1U!
#283
0+
0;
0C
1S
1c
0{
0%!
1-!
1E!
1M!
0U!
1G"
#284
1+
13
1C
0c
0-!
15!
1U!
1e!
0G"
#285
0+
0C
0S
0k
0s
1{
1%!
1=!
0E!
0M!
0e!
#286
1#
1+
1;
1C
0K
1S
1c
1-!
05!
0U!
#287
0#
0+
03
0;
0C
1K
0S
0c
1s
0{
0%!
0=!
1E!
1M!
#288
1#
1+
13
1C
1c
1k
0s
1{
0-!
1=!
0E!
1U!
1m!
#289
0#
03
0K
1[
0k
1%!
1-!
15!
0M!
0U!
0m!
#290
1#
0[
0{
0%!
0-!
05!
1E!
1M!
1U!
1]!
#291
0+
1[
0c
1k
1{
1%!
15!
0E!
0M!
0]!
#292
0#
13
1;
0C
1S
0k
1s
0%!
1-!
05!
0=!
1M!
0U!
#293
1#
1K
0[
1k
0{
1E!
1G"
#294
0#
03
0;
0S
1c
1{
1%!
0-!
15!
0E!
0M!
1U!
0G"
#295
13
0K
1S
1[
0c
0k
0{
05!
1E!
#296
1K
0[
1c
1k
0%!
1M!
#297
0K
0S
1{
1%!
0E!
0M!
#298
1#
1+
03
1;
1C
1[
0{
0%!
1E!
1M!
1e!
#299
0+
13
0C
1S
0[
0c
0k
1{
1%!
15!
0E!
0M!
0e!
#300
0#
1+
1K
1[
1c
1k
0s
0%!
1-!
05!
1=!
1M!
0U!
#301
1#
0+
03
0;
1s
1%!
0-!
0=!
0M!
1U!
17"
#302
13
1;
1C
0K
0k
0s
15!
1=!
1/"
07"
#303
0#
1+
03
0S
1k
0{
0%!
1E!
1M!
0/"
#304
1#
0;
0C
1K
1s
1{
1%!
1-!
05!
0=!
0E!
0M!
0U!
#305
0#
0+
1C
0K
1S
0[
0c
0-!
1U!
#306
1#
1+
1[
0s
0%!
1-!
1=!
1M!
0U!
#307
0#
13
1K
0S
0[
1c
0k
1%!
0M!
#308
0+
1;
0C
1S
1[
0c
0{
0-!
1E!
1U!
#309
1#
1+
03
0;
0S
1k
1s
1{
1-!
0=!
0E!
0U!
#310
0#
0+
13
1C
0K
1S
0k
0s
0{
0-!
1=!
1E!
1U!
1}!
#311
03
1;
0C
0[
1c
1{
1-!
15!
0E!
0U!
0}!
#312
13
0;
0S
1[
0c
1k
0{
0%!
0-!
05!
1E!
1M!
1U!
#313
1+
03
1C
1K
1c
1{
1%!
0E!
0M!
#314
0+
13
1;
0C
0K
1S
0c
0k
1-!
0U!
#315
1#
1+
0;
0S
0[
1c
1s
0{
0%!
0=!
1E!
1M!
#316
1K
1S
0-!
1U!
1e!
#317
0+
1C
0K
0S
0c
1k
0s
1{
1%!
1-!
15!
1=!
0E!
0M!
0U!
0e!
#318
0#
1+
1;
1S
1[
1c
0k
1s
05!
0=!
#319
1#
0;
0S
0c
1k
0%!
1M!
#320
0#
03
1K
0[
0-!
1U!
#321
13
1;
0C
0K
1S
0k
1%!
0M!
#322
0;
1K
1[
1c
1k
0%!
1M!
#323
0+
1;
1C
0K
0S
0[
0k
0s
1-!
1=!
0U!
#324
1+
0;
0C
1S
0{
1%!
1E!
0M!
#325
1#
03
1K
1[
1k
1s
0=!
#326
0#
0[
0k
1{
0%!
0E!
1M!
#327
1#
1;
0K
0s
1%!
1=!
0M!
#328
13
1K
0S
1[
1k
1s
0{
0-!
0=!
1E!
1U!
1'"
#329
0K
0[
0c
1-!
15!
0U!
0'"
#330
0+
03
0;
1C
1K
1c
0k
0-!
05!
1U!
1'"
#331
0#
13
0K
1S
1[
0c
1k
1{
0%!
15!
0E!
1M!
0'"
#332
1#
1+
0S
1c
0k
0{
05!
1E!
1e!
#333
0#
03
1;
1K
1S
0[
0c
1%!
1-!
15!
0M!
0U!
0e!
#334
1#
13
0;
0C
0S
1[
1c
1k
0s
05!
1=!
#335
0+
1;
1C
0K
1s
1{
0=!
0E!
#336
0#
03
1K
0c
0k
#337
1+
13
0K
0[
1k
0{
0%!
1E!
1M!
1G"
#338
1#
0+
03
0C
1S
1c
1%!
0-!
15!
0M!
1U!
0G"
#339
1+
1K
0S
1[
0%!
1-!
05!
1M!
0U!
1G"
#340
0#
0+
0K
1S
0c
0k
1{
1%!
0-!
15!
0E!
0M!
1U!
17"
0G"
#341
1#
13
1C
1K
0S
1k
0s
0%!
1=!
1M!
1m!
07"
#342
0C
1S
1c
0k
1-!
0U!
0m!
#343
0#
1+
0;
1C
0K
1k
05!
#344
1#
0+
0C
0S
0{
1%!
0-!
1E!
0M!
1U!
#345
1+
1;
1S
0k
0%!
1-!
1M!
0U!
1?"
#346
0#
0+
03
1C
1K
1k
0-!
15!
1U!
0?"
#347
1+
0C
0S
0[
0c
0k
1{
05!
0E!
#348
1#
0+
13
1C
1s
1%!
0=!
0M!
#349
03
1k
0s
0{
1=!
1E!
1}!
#350
1+
13
0C
0K
1[
1s
15!
0=!
0}!
#351
0#
0+
03
1K
1S
0[
0s
0%!
05!
1=!
1M!
#352
1#
1+
13
0;
1C
0K
1[
0k
1%!
1-!
0M!
0U!
#353
0+
1;
0C
0S
1c
1k
1s
1{
0=!
0E!
#354
1+
0;
1C
1S
0[
0c
0k
0%!
1M!
#355
03
1K
1c
0{
1%!
0-!
1E!
0M!
1U!
1'"
#356
0+
13
1;
0C
0K
1[
1{
15!
0E!
0'"
17"
#357
0#
1+
0;
1C
1K
0S
0[
0c
0s
0{
0%!
1-!
1=!
1E!
1M!
0U!
07"
#358
0C
0K
1S
1c
1s
1%!
0-!
05!
0=!
0M!
1U!
#359
1#
0+
03
1C
1K
0S
0c
0%!
1-!
1M!
0U!
#360
0#
13
1;
0C
0K
1S
1c
0s
1=!
1?"
#361
1+
1C
1K
1[
0c
1k
1s
0-!
15!
0=!
1U!
1e!
0?"
#362
0+
03
0S
1c
1%!
1-!
0M!
0U!
0e!
#363
1+
0;
0[
0c
05!
#364
13
1S
0%!
0-!
1M!
1U!
1e!
#365
1;
0s
1%!
15!
1=!
0M!
0e!
1}!
#366
0+
0;
0K
0k
1s
0%!
0=!
1M!
0}!
#367
1;
0C
0S
1[
1k
1%!
1-!
05!
0M!
0U!
#368
1#
1c
1{
0-!
0E!
1U!
17"
#369
1+
0;
1S
0[
0c
0{
0%!
15!
1E!
1M!
1e!
07"
#370
1C
1K
1[
1c
0s
1=!
1]!
0e!
#371
0+
03
1;
0k
1s
1%!
0=!
0M!
0]!
1'"
#372
0#
1+
0K
0[
1k
0s
0%!
1=!
1M!
0'"
#373
1#
0;
1K
0c
0k
1-!
05!
0U!
#374
0#
0K
0S
1k
1{
0-!
0E!
1U!
#375
13
1;
0C
1K
1S
1[
1s
1%!
1-!
0=!
0M!
0U!
#376
1#
0+
1C
0[
1c
0s
0{
1=!
1E!
#377
1+
0C
0K
0S
0c
0k
1s
0=!
#378
0+
03
0;
1K
1S
1k
0s
0%!
1=!
1M!
#379
0#
1+
1;
1C
1[
1%!
0M!
#380
0+
0;
0S
0k
1s
1{
0-!
0=!
0E!
1U!
17"
#381
1#
1+
13
1;
0[
1k
0{
1-!
15!
1E!
0U!
07"
#382
0#
0+
1S
1{
05!
0E!
#383
0C
0K
0S
1[
1c
0k
0%!
0-!
1M!
1U!
1u!
#384
1+
03
0;
1C
1K
1S
0[
0c
0s
15!
1=!
0u!
